novikovtv_parser_yandex/__init__.py
novikovtv_parser_yandex/parsers/__init__.py
novikovtv_parser_yandex/parsers/_yandex_deferred_search_api.py
novikovtv_parser_yandex/parsers/search_links_parser.py
novikovtv_parser_yandex/parsers/site_parser.py
novikovtv_parser_yandex/parsers/yandex_text_search_api.py
novikovtv_parser_yandex/parsers/models/__init__.py
novikovtv_parser_yandex/parsers/models/operation.py
novikovtv_parser_yandex/parsers/models/site_data.py
novikovtv_parser_yandex/parsers/models/search_request/__init__.py
novikovtv_parser_yandex/parsers/models/search_request/search_additional_classes.py
novikovtv_parser_yandex/parsers/models/search_request/search_request.py
novikovtv_parser_yandex/parsers/yandex_api_lib/__init__.py
novikovtv_parser_yandex/parsers/yandex_api_lib/constants.py
novikovtv_parser_yandex/parsers/yandex_api_lib/exceptions.py
novikovtv_parser_yandex/parsers/yandex_api_lib/yandex_api.py
novikovtv_parser_yandex/util/__init__.py
novikovtv_parser_yandex/util/singleton.py
novikovtv_parser_yandex-1.0.16.dist-info/METADATA
novikovtv_parser_yandex-1.0.16.dist-info/WHEEL
novikovtv_parser_yandex-1.0.16.dist-info/licenses/LICENSE
novikovtv_parser_yandex-1.0.16.dist-info/RECORD
