Metadata-Version: 2.4
Name: novikovtv-parser-yandex
Version: 1.0.16
Summary: This is the yandex search engine parser
Project-URL: Homepage, https://github.com/asianetsievskaya/parser-yandex
Author-email: domster704 <domster704@mail.ru>
License-Expression: MIT
License-File: LICENSE
Classifier: License :: OSI Approved :: MIT License
Classifier: Operating System :: OS Independent
Classifier: Programming Language :: Python :: 3.11
Requires-Python: >=3.11
Requires-Dist: aiohttp==3.10.11
Requires-Dist: asynciolimiter==1.2.0
Requires-Dist: beautifulsoup4==4.13.3
Requires-Dist: pydantic~=2.9.2
